aospy/__init__.py
aospy/client/__init__.py
aospy/client/apispec.py
aospy/client/client.py
aospy/client/utils.py
apstra_aospy_client-0.4.0.dist-info/DESCRIPTION.rst
apstra_aospy_client-0.4.0.dist-info/METADATA
apstra_aospy_client-0.4.0.dist-info/RECORD
apstra_aospy_client-0.4.0.dist-info/WHEEL
apstra_aospy_client-0.4.0.dist-info/metadata.json
apstra_aospy_client-0.4.0.dist-info/top_level.txt
