Metadata-Version: 2.0
Name: apstra-aospy-client
Version: 0.4.0
Summary: Python core client for AOS Server
Home-page: http://www.apstra.com
Author: Apstra, Inc.
Author-email: support@apstra.com
License: Apache 2.0
Platform: UNKNOWN
Requires-Dist: requests
Requires-Dist: retrying
Requires-Dist: six
Requires-Dist: inflection
